sleeplab_format/__init__.py
sleeplab_format/models.py
sleeplab_format/reader.py
sleeplab_format/version.py
sleeplab_format/writer.py
sleeplab_format/extractor/__init__.py
sleeplab_format/extractor/cli.py
sleeplab_format/extractor/config.py
sleeplab_format/extractor/preprocess.py
sleeplab_format/test_utils/__init__.py
sleeplab_format/test_utils/fixtures.py
sleeplab_format-0.4.1.dist-info/METADATA
sleeplab_format-0.4.1.dist-info/WHEEL
sleeplab_format-0.4.1.dist-info/entry_points.txt
sleeplab_format-0.4.1.dist-info/licenses/LICENSE
sleeplab_format-0.4.1.dist-info/RECORD
