Metadata-Version: 2.3
Name: sleeplab-format
Version: 0.4.1
Summary: An interoperable and harmonized format for polysomnography recordings.
Project-URL: Documentation, https://github.com/UEF-SmartSleepLab/sleeplab-format#readme
Project-URL: Issues, https://github.com/UEF-SmartSleepLab/sleeplab-format/issues
Project-URL: Source, https://github.com/UEF-SmartSleepLab/sleeplab-format
Author-email: Riku Huttunen <riku.huttunen@uef.fi>
License-Expression: MIT
License-File: LICENSE
Requires-Python: >=3.10
Requires-Dist: numpy
Requires-Dist: pandas
Requires-Dist: pyarrow
Requires-Dist: pydantic>=2.0
Requires-Dist: pyyaml
Requires-Dist: scipy
Requires-Dist: zarr
